{
	"Array":[
			{ "lv":"1",	"hp":"294",	"physical_ack":"48",	"physical_def":"18",	"magic_ack":"48",	"magic_def":"18",	"speed":"9",	"critper":"50",	"critper_def":"47",	"crithurt":"19",	"parryper":"50",	"parryper_dec":"47",	"hitper":"11362",	"dodgeper":"",	"crithurt_def":"",	"recover_critper":"",	"recover_critper_def":"",	"":"",	"recover_add_fix":"",	"recover_del_fix":"",	"recover_add_per":"",	"recover_del_per":"",	"rage_add_fix":"",	"rage_del_fix":"",	"rage_add_per":"",	"rage_del_per":"" },
			{ "lv":"2",	"hp":"322",	"physical_ack":"53",	"physical_def":"20",	"magic_ack":"53",	"magic_def":"20",	"speed":"10",	"critper":"100",	"critper_def":"95",	"crithurt":"39",	"parryper":"100",	"parryper_dec":"95",	"hitper":"11390",	"dodgeper":"",	"crithurt_def":"",	"recover_critper":"",	"recover_critper_def":"",	"":"",	"recover_add_fix":"",	"recover_del_fix":"",	"recover_add_per":"",	"recover_del_per":"",	"rage_add_fix":"",	"rage_del_fix":"",	"rage_add_per":"",	"rage_del_per":"" },
			{ "lv":"3",	"hp":"350",	"physical_ack":"58",	"physical_def":"22",	"magic_ack":"58",	"magic_def":"22",	"speed":"11",	"critper":"149",	"critper_def":"143",	"crithurt":"58",	"parryper":"149",	"parryper_dec":"143",	"hitper":"11419",	"dodgeper":"",	"crithurt_def":"",	"recover_critper":"",	"recover_critper_def":"",	"":"",	"recover_add_fix":"",	"recover_del_fix":"",	"recover_add_per":"",	"recover_del_per":"",	"rage_add_fix":"",	"rage_del_fix":"",	"rage_add_per":"",	"rage_del_per":"" },
			{ "lv":"4",	"hp":"385",	"physical_ack":"62",	"physical_def":"23",	"magic_ack":"62",	"magic_def":"23",	"speed":"12",	"critper":"199",	"critper_def":"191",	"crithurt":"77",	"parryper":"199",	"parryper_dec":"191",	"hitper":"11447",	"dodgeper":"",	"crithurt_def":"",	"recover_critper":"",	"recover_critper_def":"",	"":"",	"recover_add_fix":"",	"recover_del_fix":"",	"recover_add_per":"",	"recover_del_per":"",	"rage_add_fix":"",	"rage_del_fix":"",	"rage_add_per":"",	"rage_del_per":"" },
			{ "lv":"5",	"hp":"413",	"physical_ack":"67",	"physical_def":"25",	"magic_ack":"67",	"magic_def":"25",	"speed":"13",	"critper":"249",	"critper_def":"238",	"crithurt":"97",	"parryper":"249",	"parryper_dec":"238",	"hitper":"11475",	"dodgeper":"",	"crithurt_def":"",	"recover_critper":"",	"recover_critper_def":"",	"":"",	"recover_add_fix":"",	"recover_del_fix":"",	"recover_add_per":"",	"recover_del_per":"",	"rage_add_fix":"",	"rage_del_fix":"",	"rage_add_per":"",	"rage_del_per":"" },
			{ "lv":"6",	"hp":"441",	"physical_ack":"72",	"physical_def":"27",	"magic_ack":"72",	"magic_def":"27",	"speed":"14",	"critper":"299",	"critper_def":"285",	"crithurt":"115",	"parryper":"299",	"parryper_dec":"285",	"hitper":"11503",	"dodgeper":"",	"crithurt_def":"",	"recover_critper":"",	"recover_critper_def":"",	"":"",	"recover_add_fix":"",	"recover_del_fix":"",	"recover_add_per":"",	"recover_del_per":"",	"rage_add_fix":"",	"rage_del_fix":"",	"rage_add_per":"",	"rage_del_per":"" },
			{ "lv":"7",	"hp":"469",	"physical_ack":"77",	"physical_def":"29",	"magic_ack":"77",	"magic_def":"29",	"speed":"15",	"critper":"349",	"critper_def":"333",	"crithurt":"135",	"parryper":"349",	"parryper_dec":"333",	"hitper":"11532",	"dodgeper":"",	"crithurt_def":"",	"recover_critper":"",	"recover_critper_def":"",	"":"",	"recover_add_fix":"",	"recover_del_fix":"",	"recover_add_per":"",	"recover_del_per":"",	"rage_add_fix":"",	"rage_del_fix":"",	"rage_add_per":"",	"rage_del_per":"" },
			{ "lv":"8",	"hp":"497",	"physical_ack":"82",	"physical_def":"31",	"magic_ack":"82",	"magic_def":"31",	"speed":"16",	"critper":"399",	"critper_def":"381",	"crithurt":"154",	"parryper":"399",	"parryper_dec":"381",	"hitper":"11560",	"dodgeper":"",	"crithurt_def":"",	"recover_critper":"",	"recover_critper_def":"",	"":"",	"recover_add_fix":"",	"recover_del_fix":"",	"recover_add_per":"",	"recover_del_per":"",	"rage_add_fix":"",	"rage_del_fix":"",	"rage_add_per":"",	"rage_del_per":"" },
			{ "lv":"9",	"hp":"532",	"physical_ack":"86",	"physical_def":"32",	"magic_ack":"86",	"magic_def":"32",	"speed":"17",	"critper":"449",	"critper_def":"429",	"crithurt":"173",	"parryper":"449",	"parryper_dec":"429",	"hitper":"11589",	"dodgeper":"",	"crithurt_def":"",	"recover_critper":"",	"recover_critper_def":"",	"":"",	"recover_add_fix":"",	"recover_del_fix":"",	"recover_add_per":"",	"recover_del_per":"",	"rage_add_fix":"",	"rage_del_fix":"",	"rage_add_per":"",	"rage_del_per":"" },
			{ "lv":"10",	"hp":"560",	"physical_ack":"91",	"physical_def":"34",	"magic_ack":"91",	"magic_def":"34",	"speed":"18",	"critper":"499",	"critper_def":"476",	"crithurt":"193",	"parryper":"499",	"parryper_dec":"476",	"hitper":"11617",	"dodgeper":"",	"crithurt_def":"",	"recover_critper":"",	"recover_critper_def":"",	"":"",	"recover_add_fix":"",	"recover_del_fix":"",	"recover_add_per":"",	"recover_del_per":"",	"rage_add_fix":"",	"rage_del_fix":"",	"rage_add_per":"",	"rage_del_per":"" },
			{ "lv":"11",	"hp":"686",	"physical_ack":"112",	"physical_def":"42",	"magic_ack":"112",	"magic_def":"42",	"speed":"19",	"critper":"549",	"critper_def":"523",	"crithurt":"212",	"parryper":"549",	"parryper_dec":"523",	"hitper":"11645",	"dodgeper":"",	"crithurt_def":"",	"recover_critper":"",	"recover_critper_def":"",	"":"",	"recover_add_fix":"",	"recover_del_fix":"",	"recover_add_per":"",	"recover_del_per":"",	"rage_add_fix":"",	"rage_del_fix":"",	"rage_add_per":"",	"rage_del_per":"" },
			{ "lv":"12",	"hp":"714",	"physical_ack":"117",	"physical_def":"44",	"magic_ack":"117",	"magic_def":"44",	"speed":"20",	"critper":"599",	"critper_def":"571",	"crithurt":"231",	"parryper":"599",	"parryper_dec":"571",	"hitper":"11673",	"dodgeper":"",	"crithurt_def":"",	"recover_critper":"",	"recover_critper_def":"",	"":"",	"recover_add_fix":"",	"recover_del_fix":"",	"recover_add_per":"",	"recover_del_per":"",	"rage_add_fix":"",	"rage_del_fix":"",	"rage_add_per":"",	"rage_del_per":"" },
			{ "lv":"13",	"hp":"742",	"physical_ack":"122",	"physical_def":"46",	"magic_ack":"122",	"magic_def":"46",	"speed":"21",	"critper":"648",	"critper_def":"619",	"crithurt":"251",	"parryper":"648",	"parryper_dec":"619",	"hitper":"11702",	"dodgeper":"",	"crithurt_def":"",	"recover_critper":"",	"recover_critper_def":"",	"":"",	"recover_add_fix":"",	"recover_del_fix":"",	"recover_add_per":"",	"recover_del_per":"",	"rage_add_fix":"",	"rage_del_fix":"",	"rage_add_per":"",	"rage_del_per":"" },
			{ "lv":"14",	"hp":"777",	"physical_ack":"126",	"physical_def":"47",	"magic_ack":"126",	"magic_def":"47",	"speed":"22",	"critper":"698",	"critper_def":"667",	"crithurt":"270",	"parryper":"698",	"parryper_dec":"667",	"hitper":"11730",	"dodgeper":"",	"crithurt_def":"",	"recover_critper":"",	"recover_critper_def":"",	"":"",	"recover_add_fix":"",	"recover_del_fix":"",	"recover_add_per":"",	"recover_del_per":"",	"rage_add_fix":"",	"rage_del_fix":"",	"rage_add_per":"",	"rage_del_per":"" },
			{ "lv":"15",	"hp":"805",	"physical_ack":"131",	"physical_def":"49",	"magic_ack":"131",	"magic_def":"49",	"speed":"23",	"critper":"748",	"critper_def":"714",	"crithurt":"289",	"parryper":"748",	"parryper_dec":"714",	"hitper":"11759",	"dodgeper":"",	"crithurt_def":"",	"recover_critper":"",	"recover_critper_def":"",	"":"",	"recover_add_fix":"",	"recover_del_fix":"",	"recover_add_per":"",	"recover_del_per":"",	"rage_add_fix":"",	"rage_del_fix":"",	"rage_add_per":"",	"rage_del_per":"" },
			{ "lv":"16",	"hp":"833",	"physical_ack":"136",	"physical_def":"51",	"magic_ack":"136",	"magic_def":"51",	"speed":"24",	"critper":"798",	"critper_def":"761",	"crithurt":"308",	"parryper":"798",	"parryper_dec":"761",	"hitper":"11787",	"dodgeper":"",	"crithurt_def":"",	"recover_critper":"",	"recover_critper_def":"",	"":"",	"recover_add_fix":"",	"recover_del_fix":"",	"recover_add_per":"",	"recover_del_per":"",	"rage_add_fix":"",	"rage_del_fix":"",	"rage_add_per":"",	"rage_del_per":"" },
			{ "lv":"17",	"hp":"861",	"physical_ack":"141",	"physical_def":"53",	"magic_ack":"141",	"magic_def":"53",	"speed":"25",	"critper":"848",	"critper_def":"809",	"crithurt":"327",	"parryper":"848",	"parryper_dec":"809",	"hitper":"11815",	"dodgeper":"",	"crithurt_def":"",	"recover_critper":"",	"recover_critper_def":"",	"":"",	"recover_add_fix":"",	"recover_del_fix":"",	"recover_add_per":"",	"recover_del_per":"",	"rage_add_fix":"",	"rage_del_fix":"",	"rage_add_per":"",	"rage_del_per":"" },
			{ "lv":"18",	"hp":"889",	"physical_ack":"146",	"physical_def":"55",	"magic_ack":"146",	"magic_def":"55",	"speed":"26",	"critper":"897",	"critper_def":"857",	"crithurt":"347",	"parryper":"897",	"parryper_dec":"857",	"hitper":"11843",	"dodgeper":"",	"crithurt_def":"",	"recover_critper":"",	"recover_critper_def":"",	"":"",	"recover_add_fix":"",	"recover_del_fix":"",	"recover_add_per":"",	"recover_del_per":"",	"rage_add_fix":"",	"rage_del_fix":"",	"rage_add_per":"",	"rage_del_per":"" },
			{ "lv":"19",	"hp":"924",	"physical_ack":"150",	"physical_def":"56",	"magic_ack":"150",	"magic_def":"56",	"speed":"27",	"critper":"947",	"critper_def":"905",	"crithurt":"366",	"parryper":"947",	"parryper_dec":"905",	"hitper":"11872",	"dodgeper":"",	"crithurt_def":"",	"recover_critper":"",	"recover_critper_def":"",	"":"",	"recover_add_fix":"",	"recover_del_fix":"",	"recover_add_per":"",	"recover_del_per":"",	"rage_add_fix":"",	"rage_del_fix":"",	"rage_add_per":"",	"rage_del_per":"" },
			{ "lv":"20",	"hp":"1141",	"physical_ack":"186",	"physical_def":"70",	"magic_ack":"186",	"magic_def":"70",	"speed":"33",	"critper":"997",	"critper_def":"952",	"crithurt":"385",	"parryper":"997",	"parryper_dec":"952",	"hitper":"11900",	"dodgeper":"",	"crithurt_def":"",	"recover_critper":"",	"recover_critper_def":"",	"":"",	"recover_add_fix":"",	"recover_del_fix":"",	"recover_add_per":"",	"recover_del_per":"",	"rage_add_fix":"",	"rage_del_fix":"",	"rage_add_per":"",	"rage_del_per":"" },
			{ "lv":"21",	"hp":"1386",	"physical_ack":"228",	"physical_def":"86",	"magic_ack":"228",	"magic_def":"86",	"speed":"41",	"critper":"1047",	"critper_def":"999",	"crithurt":"405",	"parryper":"1047",	"parryper_dec":"999",	"hitper":"11929",	"dodgeper":"",	"crithurt_def":"",	"recover_critper":"",	"recover_critper_def":"",	"":"",	"recover_add_fix":"",	"recover_del_fix":"",	"recover_add_per":"",	"recover_del_per":"",	"rage_add_fix":"",	"rage_del_fix":"",	"rage_add_per":"",	"rage_del_per":"" },
			{ "lv":"22",	"hp":"1491",	"physical_ack":"243",	"physical_def":"91",	"magic_ack":"243",	"magic_def":"91",	"speed":"45",	"critper":"1097",	"critper_def":"1047",	"crithurt":"424",	"parryper":"1097",	"parryper_dec":"1047",	"hitper":"11957",	"dodgeper":"",	"crithurt_def":"",	"recover_critper":"",	"recover_critper_def":"",	"":"",	"recover_add_fix":"",	"recover_del_fix":"",	"recover_add_per":"",	"recover_del_per":"",	"rage_add_fix":"",	"rage_del_fix":"",	"rage_add_per":"",	"rage_del_per":"" },
			{ "lv":"23",	"hp":"1519",	"physical_ack":"250",	"physical_def":"94",	"magic_ack":"250",	"magic_def":"94",	"speed":"46",	"critper":"1147",	"critper_def":"1095",	"crithurt":"443",	"parryper":"1147",	"parryper_dec":"1095",	"hitper":"11985",	"dodgeper":"",	"crithurt_def":"",	"recover_critper":"",	"recover_critper_def":"",	"":"",	"recover_add_fix":"",	"recover_del_fix":"",	"recover_add_per":"",	"recover_del_per":"",	"rage_add_fix":"",	"rage_del_fix":"",	"rage_add_per":"",	"rage_del_per":"" },
			{ "lv":"24",	"hp":"1715",	"physical_ack":"280",	"physical_def":"105",	"magic_ack":"280",	"magic_def":"105",	"speed":"53",	"critper":"1197",	"critper_def":"1143",	"crithurt":"463",	"parryper":"1197",	"parryper_dec":"1143",	"hitper":"12013",	"dodgeper":"",	"crithurt_def":"",	"recover_critper":"",	"recover_critper_def":"",	"":"",	"recover_add_fix":"",	"recover_del_fix":"",	"recover_add_per":"",	"recover_del_per":"",	"rage_add_fix":"",	"rage_del_fix":"",	"rage_add_per":"",	"rage_del_per":"" },
			{ "lv":"25",	"hp":"1750",	"physical_ack":"285",	"physical_def":"107",	"magic_ack":"285",	"magic_def":"107",	"speed":"54",	"critper":"1247",	"critper_def":"1190",	"crithurt":"482",	"parryper":"1247",	"parryper_dec":"1190",	"hitper":"12042",	"dodgeper":"",	"crithurt_def":"",	"recover_critper":"",	"recover_critper_def":"",	"":"",	"recover_add_fix":"",	"recover_del_fix":"",	"recover_add_per":"",	"recover_del_per":"",	"rage_add_fix":"",	"rage_del_fix":"",	"rage_add_per":"",	"rage_del_per":"" },
			{ "lv":"26",	"hp":"2170",	"physical_ack":"321",	"physical_def":"121",	"magic_ack":"321",	"magic_def":"121",	"speed":"58",	"critper":"1297",	"critper_def":"1237",	"crithurt":"501",	"parryper":"1297",	"parryper_dec":"1237",	"hitper":"12070",	"dodgeper":"",	"crithurt_def":"",	"recover_critper":"",	"recover_critper_def":"",	"":"",	"recover_add_fix":"",	"recover_del_fix":"",	"recover_add_per":"",	"recover_del_per":"",	"rage_add_fix":"",	"rage_del_fix":"",	"rage_add_per":"",	"rage_del_per":"" },
			{ "lv":"27",	"hp":"2205",	"physical_ack":"327",	"physical_def":"123",	"magic_ack":"327",	"magic_def":"123",	"speed":"59",	"critper":"1347",	"critper_def":"1285",	"crithurt":"520",	"parryper":"1347",	"parryper_dec":"1285",	"hitper":"12099",	"dodgeper":"",	"crithurt_def":"",	"recover_critper":"",	"recover_critper_def":"",	"":"",	"recover_add_fix":"",	"recover_del_fix":"",	"recover_add_per":"",	"recover_del_per":"",	"rage_add_fix":"",	"rage_del_fix":"",	"rage_add_per":"",	"rage_del_per":"" },
			{ "lv":"28",	"hp":"2667",	"physical_ack":"347",	"physical_def":"131",	"magic_ack":"347",	"magic_def":"131",	"speed":"62",	"critper":"1396",	"critper_def":"1333",	"crithurt":"539",	"parryper":"1396",	"parryper_dec":"1333",	"hitper":"12127",	"dodgeper":"",	"crithurt_def":"",	"recover_critper":"",	"recover_critper_def":"",	"":"",	"recover_add_fix":"",	"recover_del_fix":"",	"recover_add_per":"",	"recover_del_per":"",	"rage_add_fix":"",	"rage_del_fix":"",	"rage_add_per":"",	"rage_del_per":"" },
			{ "lv":"29",	"hp":"2709",	"physical_ack":"352",	"physical_def":"132",	"magic_ack":"352",	"magic_def":"132",	"speed":"63",	"critper":"1446",	"critper_def":"1381",	"crithurt":"559",	"parryper":"1446",	"parryper_dec":"1381",	"hitper":"12155",	"dodgeper":"",	"crithurt_def":"",	"recover_critper":"",	"recover_critper_def":"",	"":"",	"recover_add_fix":"",	"recover_del_fix":"",	"recover_add_per":"",	"recover_del_per":"",	"rage_add_fix":"",	"rage_del_fix":"",	"rage_add_per":"",	"rage_del_per":"" },
			{ "lv":"30",	"hp":"2919",	"physical_ack":"384",	"physical_def":"144",	"magic_ack":"384",	"magic_def":"144",	"speed":"70",	"critper":"1496",	"critper_def":"1428",	"crithurt":"578",	"parryper":"1496",	"parryper_dec":"1428",	"hitper":"12183",	"dodgeper":"",	"crithurt_def":"",	"recover_critper":"",	"recover_critper_def":"",	"":"",	"recover_add_fix":"",	"recover_del_fix":"",	"recover_add_per":"",	"recover_del_per":"",	"rage_add_fix":"",	"rage_del_fix":"",	"rage_add_per":"",	"rage_del_per":"" },
			{ "lv":"31",	"hp":"2954",	"physical_ack":"390",	"physical_def":"146",	"magic_ack":"390",	"magic_def":"146",	"speed":"71",	"critper":"1546",	"critper_def":"1475",	"crithurt":"597",	"parryper":"1546",	"parryper_dec":"1475",	"hitper":"12212",	"dodgeper":"",	"crithurt_def":"",	"recover_critper":"",	"recover_critper_def":"",	"":"",	"recover_add_fix":"",	"recover_del_fix":"",	"recover_add_per":"",	"recover_del_per":"",	"rage_add_fix":"",	"rage_del_fix":"",	"rage_add_per":"",	"rage_del_per":"" },
			{ "lv":"32",	"hp":"3066",	"physical_ack":"413",	"physical_def":"156",	"magic_ack":"413",	"magic_def":"156",	"speed":"75",	"critper":"1596",	"critper_def":"1523",	"crithurt":"617",	"parryper":"1596",	"parryper_dec":"1523",	"hitper":"12240",	"dodgeper":"",	"crithurt_def":"",	"recover_critper":"",	"recover_critper_def":"",	"":"",	"recover_add_fix":"",	"recover_del_fix":"",	"recover_add_per":"",	"recover_del_per":"",	"rage_add_fix":"",	"rage_del_fix":"",	"rage_add_per":"",	"rage_del_per":"" },
			{ "lv":"33",	"hp":"3101",	"physical_ack":"419",	"physical_def":"158",	"magic_ack":"419",	"magic_def":"158",	"speed":"76",	"critper":"1645",	"critper_def":"1571",	"crithurt":"636",	"parryper":"1645",	"parryper_dec":"1571",	"hitper":"12269",	"dodgeper":"",	"crithurt_def":"",	"recover_critper":"",	"recover_critper_def":"",	"":"",	"recover_add_fix":"",	"recover_del_fix":"",	"recover_add_per":"",	"recover_del_per":"",	"rage_add_fix":"",	"rage_del_fix":"",	"rage_add_per":"",	"rage_del_per":"" },
			{ "lv":"34",	"hp":"3353",	"physical_ack":"454",	"physical_def":"170",	"magic_ack":"454",	"magic_def":"170",	"speed":"83",	"critper":"1695",	"critper_def":"1619",	"crithurt":"655",	"parryper":"1695",	"parryper_dec":"1619",	"hitper":"12297",	"dodgeper":"",	"crithurt_def":"",	"recover_critper":"",	"recover_critper_def":"",	"":"",	"recover_add_fix":"",	"recover_del_fix":"",	"recover_add_per":"",	"recover_del_per":"",	"rage_add_fix":"",	"rage_del_fix":"",	"rage_add_per":"",	"rage_del_per":"" },
			{ "lv":"35",	"hp":"3507",	"physical_ack":"482",	"physical_def":"181",	"magic_ack":"482",	"magic_def":"181",	"speed":"89",	"critper":"1745",	"critper_def":"1666",	"crithurt":"675",	"parryper":"1745",	"parryper_dec":"1666",	"hitper":"12325",	"dodgeper":"",	"crithurt_def":"",	"recover_critper":"",	"recover_critper_def":"",	"":"",	"recover_add_fix":"",	"recover_del_fix":"",	"recover_add_per":"",	"recover_del_per":"",	"rage_add_fix":"",	"rage_del_fix":"",	"rage_add_per":"",	"rage_del_per":"" },
			{ "lv":"36",	"hp":"4151",	"physical_ack":"588",	"physical_def":"221",	"magic_ack":"588",	"magic_def":"221",	"speed":"105",	"critper":"1795",	"critper_def":"1713",	"crithurt":"693",	"parryper":"1795",	"parryper_dec":"1713",	"hitper":"12353",	"dodgeper":"",	"crithurt_def":"",	"recover_critper":"",	"recover_critper_def":"",	"":"",	"recover_add_fix":"",	"recover_del_fix":"",	"recover_add_per":"",	"recover_del_per":"",	"rage_add_fix":"",	"rage_del_fix":"",	"rage_add_per":"",	"rage_del_per":"" },
			{ "lv":"37",	"hp":"4242",	"physical_ack":"604",	"physical_def":"227",	"magic_ack":"604",	"magic_def":"227",	"speed":"108",	"critper":"1845",	"critper_def":"1761",	"crithurt":"713",	"parryper":"1845",	"parryper_dec":"1761",	"hitper":"12382",	"dodgeper":"",	"crithurt_def":"",	"recover_critper":"",	"recover_critper_def":"",	"":"",	"recover_add_fix":"",	"recover_del_fix":"",	"recover_add_per":"",	"recover_del_per":"",	"rage_add_fix":"",	"rage_del_fix":"",	"rage_add_per":"",	"rage_del_per":"" },
			{ "lv":"38",	"hp":"4284",	"physical_ack":"611",	"physical_def":"230",	"magic_ack":"611",	"magic_def":"230",	"speed":"110",	"critper":"1895",	"critper_def":"1809",	"crithurt":"732",	"parryper":"1895",	"parryper_dec":"1809",	"hitper":"12410",	"dodgeper":"",	"crithurt_def":"",	"recover_critper":"",	"recover_critper_def":"",	"":"",	"recover_add_fix":"",	"recover_del_fix":"",	"recover_add_per":"",	"recover_del_per":"",	"rage_add_fix":"",	"rage_del_fix":"",	"rage_add_per":"",	"rage_del_per":"" },
			{ "lv":"39",	"hp":"4459",	"physical_ack":"634",	"physical_def":"237",	"magic_ack":"634",	"magic_def":"237",	"speed":"113",	"critper":"1945",	"critper_def":"1857",	"crithurt":"751",	"parryper":"1945",	"parryper_dec":"1857",	"hitper":"12439",	"dodgeper":"",	"crithurt_def":"",	"recover_critper":"",	"recover_critper_def":"",	"":"",	"recover_add_fix":"",	"recover_del_fix":"",	"recover_add_per":"",	"recover_del_per":"",	"rage_add_fix":"",	"rage_del_fix":"",	"rage_add_per":"",	"rage_del_per":"" },
			{ "lv":"40",	"hp":"5495",	"physical_ack":"796",	"physical_def":"298",	"magic_ack":"796",	"magic_def":"298",	"speed":"143",	"critper":"1995",	"critper_def":"1904",	"crithurt":"771",	"parryper":"1995",	"parryper_dec":"1904",	"hitper":"12467",	"dodgeper":"",	"crithurt_def":"",	"recover_critper":"",	"recover_critper_def":"",	"":"",	"recover_add_fix":"",	"recover_del_fix":"",	"recover_add_per":"",	"recover_del_per":"",	"rage_add_fix":"",	"rage_del_fix":"",	"rage_add_per":"",	"rage_del_per":"" },
			{ "lv":"41",	"hp":"5642",	"physical_ack":"821",	"physical_def":"308",	"magic_ack":"821",	"magic_def":"308",	"speed":"146",	"critper":"2045",	"critper_def":"1951",	"crithurt":"790",	"parryper":"2045",	"parryper_dec":"1951",	"hitper":"12495",	"dodgeper":"",	"crithurt_def":"",	"recover_critper":"",	"recover_critper_def":"",	"":"",	"recover_add_fix":"",	"recover_del_fix":"",	"recover_add_per":"",	"recover_del_per":"",	"rage_add_fix":"",	"rage_del_fix":"",	"rage_add_per":"",	"rage_del_per":"" },
			{ "lv":"42",	"hp":"5733",	"physical_ack":"832",	"physical_def":"311",	"magic_ack":"832",	"magic_def":"311",	"speed":"149",	"critper":"2095",	"critper_def":"1999",	"crithurt":"809",	"parryper":"2095",	"parryper_dec":"1999",	"hitper":"12523",	"dodgeper":"",	"crithurt_def":"",	"recover_critper":"",	"recover_critper_def":"",	"":"",	"recover_add_fix":"",	"recover_del_fix":"",	"recover_add_per":"",	"recover_del_per":"",	"rage_add_fix":"",	"rage_del_fix":"",	"rage_add_per":"",	"rage_del_per":"" },
			{ "lv":"43",	"hp":"6230",	"physical_ack":"856",	"physical_def":"320",	"magic_ack":"856",	"magic_def":"320",	"speed":"154",	"critper":"2144",	"critper_def":"2047",	"crithurt":"829",	"parryper":"2144",	"parryper_dec":"2047",	"hitper":"12552",	"dodgeper":"",	"crithurt_def":"",	"recover_critper":"",	"recover_critper_def":"",	"":"",	"recover_add_fix":"",	"recover_del_fix":"",	"recover_add_per":"",	"recover_del_per":"",	"rage_add_fix":"",	"rage_del_fix":"",	"rage_add_per":"",	"rage_del_per":"" },
			{ "lv":"44",	"hp":"6300",	"physical_ack":"870",	"physical_def":"326",	"magic_ack":"870",	"magic_def":"326",	"speed":"155",	"critper":"2194",	"critper_def":"2095",	"crithurt":"848",	"parryper":"2194",	"parryper_dec":"2095",	"hitper":"12580",	"dodgeper":"",	"crithurt_def":"",	"recover_critper":"",	"recover_critper_def":"",	"":"",	"recover_add_fix":"",	"recover_del_fix":"",	"recover_add_per":"",	"recover_del_per":"",	"rage_add_fix":"",	"rage_del_fix":"",	"rage_add_per":"",	"rage_del_per":"" },
			{ "lv":"45",	"hp":"6503",	"physical_ack":"906",	"physical_def":"340",	"magic_ack":"906",	"magic_def":"340",	"speed":"162",	"critper":"2244",	"critper_def":"2142",	"crithurt":"867",	"parryper":"2244",	"parryper_dec":"2142",	"hitper":"12609",	"dodgeper":"",	"crithurt_def":"",	"recover_critper":"",	"recover_critper_def":"",	"":"",	"recover_add_fix":"",	"recover_del_fix":"",	"recover_add_per":"",	"recover_del_per":"",	"rage_add_fix":"",	"rage_del_fix":"",	"rage_add_per":"",	"rage_del_per":"" },
			{ "lv":"46",	"hp":"6573",	"physical_ack":"920",	"physical_def":"346",	"magic_ack":"920",	"magic_def":"346",	"speed":"164",	"critper":"2294",	"critper_def":"2189",	"crithurt":"886",	"parryper":"2294",	"parryper_dec":"2189",	"hitper":"12637",	"dodgeper":"",	"crithurt_def":"",	"recover_critper":"",	"recover_critper_def":"",	"":"",	"recover_add_fix":"",	"recover_del_fix":"",	"recover_add_per":"",	"recover_del_per":"",	"rage_add_fix":"",	"rage_del_fix":"",	"rage_add_per":"",	"rage_del_per":"" },
			{ "lv":"47",	"hp":"6755",	"physical_ack":"943",	"physical_def":"353",	"magic_ack":"943",	"magic_def":"353",	"speed":"167",	"critper":"2344",	"critper_def":"2237",	"crithurt":"905",	"parryper":"2344",	"parryper_dec":"2237",	"hitper":"12665",	"dodgeper":"",	"crithurt_def":"",	"recover_critper":"",	"recover_critper_def":"",	"":"",	"recover_add_fix":"",	"recover_del_fix":"",	"recover_add_per":"",	"recover_del_per":"",	"rage_add_fix":"",	"rage_del_fix":"",	"rage_add_per":"",	"rage_del_per":"" },
			{ "lv":"48",	"hp":"6839",	"physical_ack":"955",	"physical_def":"357",	"magic_ack":"955",	"magic_def":"357",	"speed":"170",	"critper":"2393",	"critper_def":"2285",	"crithurt":"925",	"parryper":"2393",	"parryper_dec":"2285",	"hitper":"12693",	"dodgeper":"",	"crithurt_def":"",	"recover_critper":"",	"recover_critper_def":"",	"":"",	"recover_add_fix":"",	"recover_del_fix":"",	"recover_add_per":"",	"recover_del_per":"",	"rage_add_fix":"",	"rage_del_fix":"",	"rage_add_per":"",	"rage_del_per":"" },
			{ "lv":"49",	"hp":"7070",	"physical_ack":"996",	"physical_def":"373",	"magic_ack":"996",	"magic_def":"373",	"speed":"177",	"critper":"2443",	"critper_def":"2333",	"crithurt":"944",	"parryper":"2443",	"parryper_dec":"2333",	"hitper":"12722",	"dodgeper":"",	"crithurt_def":"",	"recover_critper":"",	"recover_critper_def":"",	"":"",	"recover_add_fix":"",	"recover_del_fix":"",	"recover_add_per":"",	"recover_del_per":"",	"rage_add_fix":"",	"rage_del_fix":"",	"rage_add_per":"",	"rage_del_per":"" },
			{ "lv":"50",	"hp":"8904",	"physical_ack":"1316",	"physical_def":"479",	"magic_ack":"1316",	"magic_def":"479",	"speed":"223",	"critper":"2493",	"critper_def":"2380",	"crithurt":"963",	"parryper":"2493",	"parryper_dec":"2380",	"hitper":"12750",	"dodgeper":"",	"crithurt_def":"",	"recover_critper":"",	"recover_critper_def":"",	"":"",	"recover_add_fix":"",	"recover_del_fix":"",	"recover_add_per":"",	"recover_del_per":"",	"rage_add_fix":"",	"rage_del_fix":"",	"rage_add_per":"",	"rage_del_per":"" },
			{ "lv":"51",	"hp":"8981",	"physical_ack":"1333",	"physical_def":"487",	"magic_ack":"1333",	"magic_def":"487",	"speed":"225",	"critper":"2543",	"critper_def":"2427",	"crithurt":"983",	"parryper":"2543",	"parryper_dec":"2427",	"hitper":"12779",	"dodgeper":"",	"crithurt_def":"",	"recover_critper":"",	"recover_critper_def":"",	"":"",	"recover_add_fix":"",	"recover_del_fix":"",	"recover_add_per":"",	"recover_del_per":"",	"rage_add_fix":"",	"rage_del_fix":"",	"rage_add_per":"",	"rage_del_per":"" },
			{ "lv":"52",	"hp":"9205",	"physical_ack":"1365",	"physical_def":"498",	"magic_ack":"1365",	"magic_def":"498",	"speed":"232",	"critper":"2593",	"critper_def":"2475",	"crithurt":"1002",	"parryper":"2593",	"parryper_dec":"2475",	"hitper":"12807",	"dodgeper":"",	"crithurt_def":"",	"recover_critper":"",	"recover_critper_def":"",	"":"",	"recover_add_fix":"",	"recover_del_fix":"",	"recover_add_per":"",	"recover_del_per":"",	"rage_add_fix":"",	"rage_del_fix":"",	"rage_add_per":"",	"rage_del_per":"" },
			{ "lv":"53",	"hp":"9303",	"physical_ack":"1379",	"physical_def":"503",	"magic_ack":"1379",	"magic_def":"503",	"speed":"235",	"critper":"2643",	"critper_def":"2523",	"crithurt":"1021",	"parryper":"2643",	"parryper_dec":"2523",	"hitper":"12835",	"dodgeper":"",	"crithurt_def":"",	"recover_critper":"",	"recover_critper_def":"",	"":"",	"recover_add_fix":"",	"recover_del_fix":"",	"recover_add_per":"",	"recover_del_per":"",	"rage_add_fix":"",	"rage_del_fix":"",	"rage_add_per":"",	"rage_del_per":"" },
			{ "lv":"54",	"hp":"9618",	"physical_ack":"1440",	"physical_def":"528",	"magic_ack":"1440",	"magic_def":"528",	"speed":"244",	"critper":"2693",	"critper_def":"2571",	"crithurt":"1041",	"parryper":"2693",	"parryper_dec":"2571",	"hitper":"12863",	"dodgeper":"",	"crithurt_def":"",	"recover_critper":"",	"recover_critper_def":"",	"":"",	"recover_add_fix":"",	"recover_del_fix":"",	"recover_add_per":"",	"recover_del_per":"",	"rage_add_fix":"",	"rage_del_fix":"",	"rage_add_per":"",	"rage_del_per":"" },
			{ "lv":"55",	"hp":"9716",	"physical_ack":"1454",	"physical_def":"532",	"magic_ack":"1454",	"magic_def":"532",	"speed":"247",	"critper":"2743",	"critper_def":"2618",	"crithurt":"1060",	"parryper":"2743",	"parryper_dec":"2618",	"hitper":"12892",	"dodgeper":"",	"crithurt_def":"",	"recover_critper":"",	"recover_critper_def":"",	"":"",	"recover_add_fix":"",	"recover_del_fix":"",	"recover_add_per":"",	"recover_del_per":"",	"rage_add_fix":"",	"rage_del_fix":"",	"rage_add_per":"",	"rage_del_per":"" },
			{ "lv":"56",	"hp":"11144",	"physical_ack":"1693",	"physical_def":"623",	"magic_ack":"1693",	"magic_def":"623",	"speed":"291",	"critper":"2793",	"critper_def":"2665",	"crithurt":"1079",	"parryper":"2793",	"parryper_dec":"2665",	"hitper":"12920",	"dodgeper":"",	"crithurt_def":"",	"recover_critper":"",	"recover_critper_def":"",	"":"",	"recover_add_fix":"",	"recover_del_fix":"",	"recover_add_per":"",	"recover_del_per":"",	"rage_add_fix":"",	"rage_del_fix":"",	"rage_add_per":"",	"rage_del_per":"" },
			{ "lv":"57",	"hp":"11270",	"physical_ack":"1710",	"physical_def":"629",	"magic_ack":"1710",	"magic_def":"629",	"speed":"294",	"critper":"2843",	"critper_def":"2713",	"crithurt":"1098",	"parryper":"2843",	"parryper_dec":"2713",	"hitper":"12949",	"dodgeper":"",	"crithurt_def":"",	"recover_critper":"",	"recover_critper_def":"",	"":"",	"recover_add_fix":"",	"recover_del_fix":"",	"recover_add_per":"",	"recover_del_per":"",	"rage_add_fix":"",	"rage_del_fix":"",	"rage_add_per":"",	"rage_del_per":"" },
			{ "lv":"58",	"hp":"11900",	"physical_ack":"1749",	"physical_def":"642",	"magic_ack":"1749",	"magic_def":"642",	"speed":"300",	"critper":"2892",	"critper_def":"2761",	"crithurt":"1117",	"parryper":"2892",	"parryper_dec":"2761",	"hitper":"12977",	"dodgeper":"",	"crithurt_def":"",	"recover_critper":"",	"recover_critper_def":"",	"":"",	"recover_add_fix":"",	"recover_del_fix":"",	"recover_add_per":"",	"recover_del_per":"",	"rage_add_fix":"",	"rage_del_fix":"",	"rage_add_per":"",	"rage_del_per":"" },
			{ "lv":"59",	"hp":"11998",	"physical_ack":"1770",	"physical_def":"651",	"magic_ack":"1770",	"magic_def":"651",	"speed":"303",	"critper":"2942",	"critper_def":"2809",	"crithurt":"1137",	"parryper":"2942",	"parryper_dec":"2809",	"hitper":"13005",	"dodgeper":"",	"crithurt_def":"",	"recover_critper":"",	"recover_critper_def":"",	"":"",	"recover_add_fix":"",	"recover_del_fix":"",	"recover_add_per":"",	"recover_del_per":"",	"rage_add_fix":"",	"rage_del_fix":"",	"rage_add_per":"",	"rage_del_per":"" },
			{ "lv":"60",	"hp":"12642",	"physical_ack":"1871",	"physical_def":"687",	"magic_ack":"1871",	"magic_def":"687",	"speed":"323",	"critper":"2992",	"critper_def":"2856",	"crithurt":"1156",	"parryper":"2992",	"parryper_dec":"2856",	"hitper":"13033",	"dodgeper":"",	"crithurt_def":"",	"recover_critper":"",	"recover_critper_def":"",	"":"",	"recover_add_fix":"",	"recover_del_fix":"",	"recover_add_per":"",	"recover_del_per":"",	"rage_add_fix":"",	"rage_del_fix":"",	"rage_add_per":"",	"rage_del_per":"" },
			{ "lv":"61",	"hp":"12747",	"physical_ack":"1892",	"physical_def":"696",	"magic_ack":"1892",	"magic_def":"696",	"speed":"326",	"critper":"3042",	"critper_def":"2903",	"crithurt":"1175",	"parryper":"3042",	"parryper_dec":"2903",	"hitper":"13062",	"dodgeper":"",	"crithurt_def":"",	"recover_critper":"",	"recover_critper_def":"",	"":"",	"recover_add_fix":"",	"recover_del_fix":"",	"recover_add_per":"",	"recover_del_per":"",	"rage_add_fix":"",	"rage_del_fix":"",	"rage_add_per":"",	"rage_del_per":"" },
			{ "lv":"62",	"hp":"13041",	"physical_ack":"1937",	"physical_def":"713",	"magic_ack":"1937",	"magic_def":"713",	"speed":"335",	"critper":"3092",	"critper_def":"2951",	"crithurt":"1195",	"parryper":"3092",	"parryper_dec":"2951",	"hitper":"13090",	"dodgeper":"",	"crithurt_def":"",	"recover_critper":"",	"recover_critper_def":"",	"":"",	"recover_add_fix":"",	"recover_del_fix":"",	"recover_add_per":"",	"recover_del_per":"",	"rage_add_fix":"",	"rage_del_fix":"",	"rage_add_per":"",	"rage_del_per":"" },
			{ "lv":"63",	"hp":"13167",	"physical_ack":"1955",	"physical_def":"719",	"magic_ack":"1955",	"magic_def":"719",	"speed":"338",	"critper":"3141",	"critper_def":"2999",	"crithurt":"1214",	"parryper":"3141",	"parryper_dec":"2999",	"hitper":"13119",	"dodgeper":"",	"crithurt_def":"",	"recover_critper":"",	"recover_critper_def":"",	"":"",	"recover_add_fix":"",	"recover_del_fix":"",	"recover_add_per":"",	"recover_del_per":"",	"rage_add_fix":"",	"rage_del_fix":"",	"rage_add_per":"",	"rage_del_per":"" },
			{ "lv":"64",	"hp":"13622",	"physical_ack":"2034",	"physical_def":"750",	"magic_ack":"2034",	"magic_def":"750",	"speed":"351",	"critper":"3191",	"critper_def":"3047",	"crithurt":"1233",	"parryper":"3191",	"parryper_dec":"3047",	"hitper":"13147",	"dodgeper":"",	"crithurt_def":"",	"recover_critper":"",	"recover_critper_def":"",	"":"",	"recover_add_fix":"",	"recover_del_fix":"",	"recover_add_per":"",	"recover_del_per":"",	"rage_add_fix":"",	"rage_del_fix":"",	"rage_add_per":"",	"rage_del_per":"" },
			{ "lv":"65",	"hp":"14217",	"physical_ack":"2129",	"physical_def":"785",	"magic_ack":"2129",	"magic_def":"785",	"speed":"368",	"critper":"3241",	"critper_def":"3094",	"crithurt":"1253",	"parryper":"3241",	"parryper_dec":"3094",	"hitper":"13175",	"dodgeper":"",	"crithurt_def":"",	"recover_critper":"",	"recover_critper_def":"",	"":"",	"recover_add_fix":"",	"recover_del_fix":"",	"recover_add_per":"",	"recover_del_per":"",	"rage_add_fix":"",	"rage_del_fix":"",	"rage_add_per":"",	"rage_del_per":"" },
			{ "lv":"66",	"hp":"14322",	"physical_ack":"2150",	"physical_def":"794",	"magic_ack":"2150",	"magic_def":"794",	"speed":"371",	"critper":"3291",	"critper_def":"3141",	"crithurt":"1271",	"parryper":"3291",	"parryper_dec":"3141",	"hitper":"13203",	"dodgeper":"",	"crithurt_def":"",	"recover_critper":"",	"recover_critper_def":"",	"":"",	"recover_add_fix":"",	"recover_del_fix":"",	"recover_add_per":"",	"recover_del_per":"",	"rage_add_fix":"",	"rage_del_fix":"",	"rage_add_per":"",	"rage_del_per":"" },
			{ "lv":"67",	"hp":"14595",	"physical_ack":"2194",	"physical_def":"810",	"magic_ack":"2194",	"magic_def":"810",	"speed":"378",	"critper":"3341",	"critper_def":"3189",	"crithurt":"1291",	"parryper":"3341",	"parryper_dec":"3189",	"hitper":"13232",	"dodgeper":"",	"crithurt_def":"",	"recover_critper":"",	"recover_critper_def":"",	"":"",	"recover_add_fix":"",	"recover_del_fix":"",	"recover_add_per":"",	"recover_del_per":"",	"rage_add_fix":"",	"rage_del_fix":"",	"rage_add_per":"",	"rage_del_per":"" },
			{ "lv":"68",	"hp":"14721",	"physical_ack":"2212",	"physical_def":"816",	"magic_ack":"2212",	"magic_def":"816",	"speed":"381",	"critper":"3391",	"critper_def":"3237",	"crithurt":"1310",	"parryper":"3391",	"parryper_dec":"3237",	"hitper":"13260",	"dodgeper":"",	"crithurt_def":"",	"recover_critper":"",	"recover_critper_def":"",	"":"",	"recover_add_fix":"",	"recover_del_fix":"",	"recover_add_per":"",	"recover_del_per":"",	"rage_add_fix":"",	"rage_del_fix":"",	"rage_add_per":"",	"rage_del_per":"" },
			{ "lv":"69",	"hp":"15211",	"physical_ack":"2294",	"physical_def":"848",	"magic_ack":"2294",	"magic_def":"848",	"speed":"396",	"critper":"3441",	"critper_def":"3285",	"crithurt":"1329",	"parryper":"3441",	"parryper_dec":"3285",	"hitper":"13289",	"dodgeper":"",	"crithurt_def":"",	"recover_critper":"",	"recover_critper_def":"",	"":"",	"recover_add_fix":"",	"recover_del_fix":"",	"recover_add_per":"",	"recover_del_per":"",	"rage_add_fix":"",	"rage_del_fix":"",	"rage_add_per":"",	"rage_del_per":"" },
			{ "lv":"70",	"hp":"15722",	"physical_ack":"2373",	"physical_def":"876",	"magic_ack":"2373",	"magic_def":"876",	"speed":"410",	"critper":"3491",	"critper_def":"3332",	"crithurt":"1349",	"parryper":"3491",	"parryper_dec":"3332",	"hitper":"13317",	"dodgeper":"",	"crithurt_def":"",	"recover_critper":"",	"recover_critper_def":"",	"":"",	"recover_add_fix":"",	"recover_del_fix":"",	"recover_add_per":"",	"recover_del_per":"",	"rage_add_fix":"",	"rage_del_fix":"",	"rage_add_per":"",	"rage_del_per":"" },
			{ "lv":"71",	"hp":"16037",	"physical_ack":"2426",	"physical_def":"896",	"magic_ack":"2426",	"magic_def":"896",	"speed":"419",	"critper":"3541",	"critper_def":"3379",	"crithurt":"1368",	"parryper":"3541",	"parryper_dec":"3379",	"hitper":"13345",	"dodgeper":"",	"crithurt_def":"",	"recover_critper":"",	"recover_critper_def":"",	"":"",	"recover_add_fix":"",	"recover_del_fix":"",	"recover_add_per":"",	"recover_del_per":"",	"rage_add_fix":"",	"rage_del_fix":"",	"rage_add_per":"",	"rage_del_per":"" },
			{ "lv":"72",	"hp":"16170",	"physical_ack":"2444",	"physical_def":"902",	"magic_ack":"2444",	"magic_def":"902",	"speed":"422",	"critper":"3591",	"critper_def":"3427",	"crithurt":"1387",	"parryper":"3591",	"parryper_dec":"3427",	"hitper":"13373",	"dodgeper":"",	"crithurt_def":"",	"recover_critper":"",	"recover_critper_def":"",	"":"",	"recover_add_fix":"",	"recover_del_fix":"",	"recover_add_per":"",	"recover_del_per":"",	"rage_add_fix":"",	"rage_del_fix":"",	"rage_add_per":"",	"rage_del_per":"" },
			{ "lv":"73",	"hp":"17199",	"physical_ack":"2498",	"physical_def":"922",	"magic_ack":"2498",	"magic_def":"922",	"speed":"433",	"critper":"3640",	"critper_def":"3475",	"crithurt":"1407",	"parryper":"3640",	"parryper_dec":"3475",	"hitper":"13402",	"dodgeper":"",	"crithurt_def":"",	"recover_critper":"",	"recover_critper_def":"",	"":"",	"recover_add_fix":"",	"recover_del_fix":"",	"recover_add_per":"",	"recover_del_per":"",	"rage_add_fix":"",	"rage_del_fix":"",	"rage_add_per":"",	"rage_del_per":"" },
			{ "lv":"74",	"hp":"17304",	"physical_ack":"2520",	"physical_def":"932",	"magic_ack":"2520",	"magic_def":"932",	"speed":"436",	"critper":"3690",	"critper_def":"3523",	"crithurt":"1426",	"parryper":"3690",	"parryper_dec":"3523",	"hitper":"13430",	"dodgeper":"",	"crithurt_def":"",	"recover_critper":"",	"recover_critper_def":"",	"":"",	"recover_add_fix":"",	"recover_del_fix":"",	"recover_add_per":"",	"recover_del_per":"",	"rage_add_fix":"",	"rage_del_fix":"",	"rage_add_per":"",	"rage_del_per":"" },
			{ "lv":"75",	"hp":"18396",	"physical_ack":"2680",	"physical_def":"979",	"magic_ack":"2680",	"magic_def":"979",	"speed":"450",	"critper":"3740",	"critper_def":"3570",	"crithurt":"1445",	"parryper":"3740",	"parryper_dec":"3570",	"hitper":"13459",	"dodgeper":"",	"crithurt_def":"",	"recover_critper":"",	"recover_critper_def":"",	"":"",	"recover_add_fix":"",	"recover_del_fix":"",	"recover_add_per":"",	"recover_del_per":"",	"rage_add_fix":"",	"rage_del_fix":"",	"rage_add_per":"",	"rage_del_per":"" },
			{ "lv":"76",	"hp":"18501",	"physical_ack":"2702",	"physical_def":"989",	"magic_ack":"2702",	"magic_def":"989",	"speed":"453",	"critper":"3790",	"critper_def":"3617",	"crithurt":"1464",	"parryper":"3790",	"parryper_dec":"3617",	"hitper":"13487",	"dodgeper":"",	"crithurt_def":"",	"recover_critper":"",	"recover_critper_def":"",	"":"",	"recover_add_fix":"",	"recover_del_fix":"",	"recover_add_per":"",	"recover_del_per":"",	"rage_add_fix":"",	"rage_del_fix":"",	"rage_add_per":"",	"rage_del_per":"" },
			{ "lv":"77",	"hp":"18858",	"physical_ack":"2758",	"physical_def":"1009",	"magic_ack":"2758",	"magic_def":"1009",	"speed":"462",	"critper":"3840",	"critper_def":"3665",	"crithurt":"1483",	"parryper":"3840",	"parryper_dec":"3665",	"hitper":"13515",	"dodgeper":"",	"crithurt_def":"",	"recover_critper":"",	"recover_critper_def":"",	"":"",	"recover_add_fix":"",	"recover_del_fix":"",	"recover_add_per":"",	"recover_del_per":"",	"rage_add_fix":"",	"rage_del_fix":"",	"rage_add_per":"",	"rage_del_per":"" },
			{ "lv":"78",	"hp":"18984",	"physical_ack":"2777",	"physical_def":"1015",	"magic_ack":"2777",	"magic_def":"1015",	"speed":"465",	"critper":"3889",	"critper_def":"3713",	"crithurt":"1503",	"parryper":"3889",	"parryper_dec":"3713",	"hitper":"13543",	"dodgeper":"",	"crithurt_def":"",	"recover_critper":"",	"recover_critper_def":"",	"":"",	"recover_add_fix":"",	"recover_del_fix":"",	"recover_add_per":"",	"recover_del_per":"",	"rage_add_fix":"",	"rage_del_fix":"",	"rage_add_per":"",	"rage_del_per":"" },
			{ "lv":"79",	"hp":"19607",	"physical_ack":"2878",	"physical_def":"1053",	"magic_ack":"2878",	"magic_def":"1053",	"speed":"485",	"critper":"3939",	"critper_def":"3761",	"crithurt":"1522",	"parryper":"3939",	"parryper_dec":"3761",	"hitper":"13572",	"dodgeper":"",	"crithurt_def":"",	"recover_critper":"",	"recover_critper_def":"",	"":"",	"recover_add_fix":"",	"recover_del_fix":"",	"recover_add_per":"",	"recover_del_per":"",	"rage_add_fix":"",	"rage_del_fix":"",	"rage_add_per":"",	"rage_del_per":"" },
			{ "lv":"80",	"hp":"27260",	"physical_ack":"3289",	"physical_def":"1317",	"magic_ack":"3289",	"magic_def":"1317",	"speed":"602",	"critper":"3989",	"critper_def":"3808",	"crithurt":"1541",	"parryper":"3989",	"parryper_dec":"3808",	"hitper":"13600",	"dodgeper":"",	"crithurt_def":"",	"recover_critper":"",	"recover_critper_def":"",	"":"",	"recover_add_fix":"",	"recover_del_fix":"",	"recover_add_per":"",	"recover_del_per":"",	"rage_add_fix":"",	"rage_del_fix":"",	"rage_add_per":"",	"rage_del_per":"" },
			{ "lv":"81",	"hp":"27413",	"physical_ack":"3316",	"physical_def":"1330",	"magic_ack":"3316",	"magic_def":"1330",	"speed":"606",	"critper":"4039",	"critper_def":"3855",	"crithurt":"1561",	"parryper":"4039",	"parryper_dec":"3855",	"hitper":"13629",	"dodgeper":"",	"crithurt_def":"",	"recover_critper":"",	"recover_critper_def":"",	"":"",	"recover_add_fix":"",	"recover_del_fix":"",	"recover_add_per":"",	"recover_del_per":"",	"rage_add_fix":"",	"rage_del_fix":"",	"rage_add_per":"",	"rage_del_per":"" },
			{ "lv":"82",	"hp":"27921",	"physical_ack":"3377",	"physical_def":"1354",	"magic_ack":"3377",	"magic_def":"1354",	"speed":"618",	"critper":"4089",	"critper_def":"3903",	"crithurt":"1580",	"parryper":"4089",	"parryper_dec":"3903",	"hitper":"13657",	"dodgeper":"",	"crithurt_def":"",	"recover_critper":"",	"recover_critper_def":"",	"":"",	"recover_add_fix":"",	"recover_del_fix":"",	"recover_add_per":"",	"recover_del_per":"",	"rage_add_fix":"",	"rage_del_fix":"",	"rage_add_per":"",	"rage_del_per":"" },
			{ "lv":"83",	"hp":"28114",	"physical_ack":"3399",	"physical_def":"1362",	"magic_ack":"3399",	"magic_def":"1362",	"speed":"622",	"critper":"4139",	"critper_def":"3951",	"crithurt":"1599",	"parryper":"4139",	"parryper_dec":"3951",	"hitper":"13685",	"dodgeper":"",	"crithurt_def":"",	"recover_critper":"",	"recover_critper_def":"",	"":"",	"recover_add_fix":"",	"recover_del_fix":"",	"recover_add_per":"",	"recover_del_per":"",	"rage_add_fix":"",	"rage_del_fix":"",	"rage_add_per":"",	"rage_del_per":"" },
			{ "lv":"84",	"hp":"29007",	"physical_ack":"3518",	"physical_def":"1411",	"magic_ack":"3518",	"magic_def":"1411",	"speed":"646",	"critper":"4189",	"critper_def":"3999",	"crithurt":"1619",	"parryper":"4189",	"parryper_dec":"3999",	"hitper":"13713",	"dodgeper":"",	"crithurt_def":"",	"recover_critper":"",	"recover_critper_def":"",	"":"",	"recover_add_fix":"",	"recover_del_fix":"",	"recover_add_per":"",	"recover_del_per":"",	"rage_add_fix":"",	"rage_del_fix":"",	"rage_add_per":"",	"rage_del_per":"" },
			{ "lv":"85",	"hp":"30207",	"physical_ack":"3587",	"physical_def":"1438",	"magic_ack":"3587",	"magic_def":"1438",	"speed":"651",	"critper":"4239",	"critper_def":"4046",	"crithurt":"1638",	"parryper":"4239",	"parryper_dec":"4046",	"hitper":"13742",	"dodgeper":"",	"crithurt_def":"",	"recover_critper":"",	"recover_critper_def":"",	"":"",	"recover_add_fix":"",	"recover_del_fix":"",	"recover_add_per":"",	"recover_del_per":"",	"rage_add_fix":"",	"rage_del_fix":"",	"rage_add_per":"",	"rage_del_per":"" },
			{ "lv":"86",	"hp":"30738",	"physical_ack":"3667",	"physical_def":"1474",	"magic_ack":"3667",	"magic_def":"1474",	"speed":"664",	"critper":"4289",	"critper_def":"4093",	"crithurt":"1657",	"parryper":"4289",	"parryper_dec":"4093",	"hitper":"13770",	"dodgeper":"",	"crithurt_def":"",	"recover_critper":"",	"recover_critper_def":"",	"":"",	"recover_add_fix":"",	"recover_del_fix":"",	"recover_add_per":"",	"recover_del_per":"",	"rage_add_fix":"",	"rage_del_fix":"",	"rage_add_per":"",	"rage_del_per":"" },
			{ "lv":"87",	"hp":"30931",	"physical_ack":"3689",	"physical_def":"1482",	"magic_ack":"3689",	"magic_def":"1482",	"speed":"669",	"critper":"4339",	"critper_def":"4141",	"crithurt":"1676",	"parryper":"4339",	"parryper_dec":"4141",	"hitper":"13799",	"dodgeper":"",	"crithurt_def":"",	"recover_critper":"",	"recover_critper_def":"",	"":"",	"recover_add_fix":"",	"recover_del_fix":"",	"recover_add_per":"",	"recover_del_per":"",	"rage_add_fix":"",	"rage_del_fix":"",	"rage_add_per":"",	"rage_del_per":"" },
			{ "lv":"88",	"hp":"32561",	"physical_ack":"3759",	"physical_def":"1509",	"magic_ack":"3759",	"magic_def":"1509",	"speed":"682",	"critper":"4388",	"critper_def":"4189",	"crithurt":"1695",	"parryper":"4388",	"parryper_dec":"4189",	"hitper":"13827",	"dodgeper":"",	"crithurt_def":"",	"recover_critper":"",	"recover_critper_def":"",	"":"",	"recover_add_fix":"",	"recover_del_fix":"",	"recover_add_per":"",	"recover_del_per":"",	"rage_add_fix":"",	"rage_del_fix":"",	"rage_add_per":"",	"rage_del_per":"" },
			{ "lv":"89",	"hp":"32730",	"physical_ack":"3784",	"physical_def":"1520",	"magic_ack":"3784",	"magic_def":"1520",	"speed":"686",	"critper":"4438",	"critper_def":"4237",	"crithurt":"1715",	"parryper":"4438",	"parryper_dec":"4237",	"hitper":"13855",	"dodgeper":"",	"crithurt_def":"",	"recover_critper":"",	"recover_critper_def":"",	"":"",	"recover_add_fix":"",	"recover_del_fix":"",	"recover_add_per":"",	"recover_del_per":"",	"rage_add_fix":"",	"rage_del_fix":"",	"rage_add_per":"",	"rage_del_per":"" },
			{ "lv":"90",	"hp":"34090",	"physical_ack":"3999",	"physical_def":"1590",	"magic_ack":"3999",	"magic_def":"1590",	"speed":"710",	"critper":"4488",	"critper_def":"4284",	"crithurt":"1734",	"parryper":"4488",	"parryper_dec":"4284",	"hitper":"13883",	"dodgeper":"",	"crithurt_def":"",	"recover_critper":"",	"recover_critper_def":"",	"":"",	"recover_add_fix":"",	"recover_del_fix":"",	"recover_add_per":"",	"recover_del_per":"",	"rage_add_fix":"",	"rage_del_fix":"",	"rage_add_per":"",	"rage_del_per":"" },
			{ "lv":"91",	"hp":"39572",	"physical_ack":"4716",	"physical_def":"1882",	"magic_ack":"4716",	"magic_def":"1882",	"speed":"843",	"critper":"4538",	"critper_def":"4331",	"crithurt":"1753",	"parryper":"4538",	"parryper_dec":"4331",	"hitper":"13912",	"dodgeper":"",	"crithurt_def":"",	"recover_critper":"",	"recover_critper_def":"",	"":"",	"recover_add_fix":"",	"recover_del_fix":"",	"recover_add_per":"",	"recover_del_per":"",	"rage_add_fix":"",	"rage_del_fix":"",	"rage_add_per":"",	"rage_del_per":"" },
			{ "lv":"92",	"hp":"40313",	"physical_ack":"4802",	"physical_def":"1914",	"magic_ack":"4802",	"magic_def":"1914",	"speed":"862",	"critper":"4588",	"critper_def":"4379",	"crithurt":"1773",	"parryper":"4588",	"parryper_dec":"4379",	"hitper":"13940",	"dodgeper":"",	"crithurt_def":"",	"recover_critper":"",	"recover_critper_def":"",	"":"",	"recover_add_fix":"",	"recover_del_fix":"",	"recover_add_per":"",	"recover_del_per":"",	"rage_add_fix":"",	"rage_del_fix":"",	"rage_add_per":"",	"rage_del_per":"" },
			{ "lv":"93",	"hp":"40563",	"physical_ack":"4829",	"physical_def":"1924",	"magic_ack":"4829",	"magic_def":"1924",	"speed":"867",	"critper":"4637",	"critper_def":"4427",	"crithurt":"1792",	"parryper":"4637",	"parryper_dec":"4427",	"hitper":"13969",	"dodgeper":"",	"crithurt_def":"",	"recover_critper":"",	"recover_critper_def":"",	"":"",	"recover_add_fix":"",	"recover_del_fix":"",	"recover_add_per":"",	"recover_del_per":"",	"rage_add_fix":"",	"rage_del_fix":"",	"rage_add_per":"",	"rage_del_per":"" },
			{ "lv":"94",	"hp":"41746",	"physical_ack":"4997",	"physical_def":"1996",	"magic_ack":"4997",	"magic_def":"1996",	"speed":"898",	"critper":"4687",	"critper_def":"4475",	"crithurt":"1811",	"parryper":"4687",	"parryper_dec":"4475",	"hitper":"13997",	"dodgeper":"",	"crithurt_def":"",	"recover_critper":"",	"recover_critper_def":"",	"":"",	"recover_add_fix":"",	"recover_del_fix":"",	"recover_add_per":"",	"recover_del_per":"",	"rage_add_fix":"",	"rage_del_fix":"",	"rage_add_per":"",	"rage_del_per":"" },
			{ "lv":"95",	"hp":"43364",	"physical_ack":"5203",	"physical_def":"2079",	"magic_ack":"5203",	"magic_def":"2079",	"speed":"940",	"critper":"4737",	"critper_def":"4522",	"crithurt":"1831",	"parryper":"4737",	"parryper_dec":"4522",	"hitper":"14025",	"dodgeper":"",	"crithurt_def":"",	"recover_critper":"",	"recover_critper_def":"",	"":"",	"recover_add_fix":"",	"recover_del_fix":"",	"recover_add_per":"",	"recover_del_per":"",	"rage_add_fix":"",	"rage_del_fix":"",	"rage_add_per":"",	"rage_del_per":"" },
			{ "lv":"96",	"hp":"43573",	"physical_ack":"5236",	"physical_def":"2094",	"magic_ack":"5236",	"magic_def":"2094",	"speed":"945",	"critper":"4787",	"critper_def":"4569",	"crithurt":"1849",	"parryper":"4787",	"parryper_dec":"4569",	"hitper":"14053",	"dodgeper":"",	"crithurt_def":"",	"recover_critper":"",	"recover_critper_def":"",	"":"",	"recover_add_fix":"",	"recover_del_fix":"",	"recover_add_per":"",	"recover_del_per":"",	"rage_add_fix":"",	"rage_del_fix":"",	"rage_add_per":"",	"rage_del_per":"" },
			{ "lv":"97",	"hp":"44274",	"physical_ack":"5322",	"physical_def":"2127",	"magic_ack":"5322",	"magic_def":"2127",	"speed":"962",	"critper":"4837",	"critper_def":"4617",	"crithurt":"1869",	"parryper":"4837",	"parryper_dec":"4617",	"hitper":"14082",	"dodgeper":"",	"crithurt_def":"",	"recover_critper":"",	"recover_critper_def":"",	"":"",	"recover_add_fix":"",	"recover_del_fix":"",	"recover_add_per":"",	"recover_del_per":"",	"rage_add_fix":"",	"rage_del_fix":"",	"rage_add_per":"",	"rage_del_per":"" },
			{ "lv":"98",	"hp":"44523",	"physical_ack":"5349",	"physical_def":"2137",	"magic_ack":"5349",	"magic_def":"2137",	"speed":"967",	"critper":"4887",	"critper_def":"4665",	"crithurt":"1888",	"parryper":"4887",	"parryper_dec":"4665",	"hitper":"14110",	"dodgeper":"",	"crithurt_def":"",	"recover_critper":"",	"recover_critper_def":"",	"":"",	"recover_add_fix":"",	"recover_del_fix":"",	"recover_add_per":"",	"recover_del_per":"",	"rage_add_fix":"",	"rage_del_fix":"",	"rage_add_per":"",	"rage_del_per":"" },
			{ "lv":"99",	"hp":"45795",	"physical_ack":"5526",	"physical_def":"2212",	"magic_ack":"5526",	"magic_def":"2212",	"speed":"1001",	"critper":"4937",	"critper_def":"4713",	"crithurt":"1907",	"parryper":"4937",	"parryper_dec":"4713",	"hitper":"14139",	"dodgeper":"",	"crithurt_def":"",	"recover_critper":"",	"recover_critper_def":"",	"":"",	"recover_add_fix":"",	"recover_del_fix":"",	"recover_add_per":"",	"recover_del_per":"",	"rage_add_fix":"",	"rage_del_fix":"",	"rage_add_per":"",	"rage_del_per":"" },
			{ "lv":"100",	"hp":"49723",	"physical_ack":"5933",	"physical_def":"2374",	"magic_ack":"5933",	"magic_def":"2374",	"speed":"1102",	"critper":"4987",	"critper_def":"4760",	"crithurt":"1927",	"parryper":"4987",	"parryper_dec":"4760",	"hitper":"14167",	"dodgeper":"",	"crithurt_def":"",	"recover_critper":"",	"recover_critper_def":"",	"":"",	"recover_add_fix":"",	"recover_del_fix":"",	"recover_add_per":"",	"recover_del_per":"",	"rage_add_fix":"",	"rage_del_fix":"",	"rage_add_per":"",	"rage_del_per":"" },
			{ "lv":"101",	"hp":"50569",	"physical_ack":"6048",	"physical_def":"2423",	"magic_ack":"6048",	"magic_def":"2423",	"speed":"1123",	"critper":"5037",	"critper_def":"4807",	"crithurt":"1946",	"parryper":"5037",	"parryper_dec":"4807",	"hitper":"14195",	"dodgeper":"",	"crithurt_def":"",	"recover_critper":"",	"recover_critper_def":"",	"":"",	"recover_add_fix":"",	"recover_del_fix":"",	"recover_add_per":"",	"recover_del_per":"",	"rage_add_fix":"",	"rage_del_fix":"",	"rage_add_per":"",	"rage_del_per":"" },
			{ "lv":"102",	"hp":"50834",	"physical_ack":"6078",	"physical_def":"2434",	"magic_ack":"6078",	"magic_def":"2434",	"speed":"1129",	"critper":"5087",	"critper_def":"4855",	"crithurt":"1965",	"parryper":"5087",	"parryper_dec":"4855",	"hitper":"14223",	"dodgeper":"",	"crithurt_def":"",	"recover_critper":"",	"recover_critper_def":"",	"":"",	"recover_add_fix":"",	"recover_del_fix":"",	"recover_add_per":"",	"recover_del_per":"",	"rage_add_fix":"",	"rage_del_fix":"",	"rage_add_per":"",	"rage_del_per":"" },
			{ "lv":"103",	"hp":"52404",	"physical_ack":"6189",	"physical_def":"2479",	"magic_ack":"6189",	"magic_def":"2479",	"speed":"1150",	"critper":"5136",	"critper_def":"4903",	"crithurt":"1985",	"parryper":"5136",	"parryper_dec":"4903",	"hitper":"14252",	"dodgeper":"",	"crithurt_def":"",	"recover_critper":"",	"recover_critper_def":"",	"":"",	"recover_add_fix":"",	"recover_del_fix":"",	"recover_add_per":"",	"recover_del_per":"",	"rage_add_fix":"",	"rage_del_fix":"",	"rage_add_per":"",	"rage_del_per":"" },
			{ "lv":"104",	"hp":"52621",	"physical_ack":"6224",	"physical_def":"2495",	"magic_ack":"6224",	"magic_def":"2495",	"speed":"1156",	"critper":"5186",	"critper_def":"4951",	"crithurt":"2004",	"parryper":"5186",	"parryper_dec":"4951",	"hitper":"14280",	"dodgeper":"",	"crithurt_def":"",	"recover_critper":"",	"recover_critper_def":"",	"":"",	"recover_add_fix":"",	"recover_del_fix":"",	"recover_add_per":"",	"recover_del_per":"",	"rage_add_fix":"",	"rage_del_fix":"",	"rage_add_per":"",	"rage_del_per":"" },
			{ "lv":"105",	"hp":"54143",	"physical_ack":"6415",	"physical_def":"2570",	"magic_ack":"6415",	"magic_def":"2570",	"speed":"1195",	"critper":"5236",	"critper_def":"4998",	"crithurt":"2023",	"parryper":"5236",	"parryper_dec":"4998",	"hitper":"14309",	"dodgeper":"",	"crithurt_def":"",	"recover_critper":"",	"recover_critper_def":"",	"":"",	"recover_add_fix":"",	"recover_del_fix":"",	"recover_add_per":"",	"recover_del_per":"",	"rage_add_fix":"",	"rage_del_fix":"",	"rage_add_per":"",	"rage_del_per":"" },
			{ "lv":"106",	"hp":"54360",	"physical_ack":"6451",	"physical_def":"2587",	"magic_ack":"6451",	"magic_def":"2587",	"speed":"1201",	"critper":"5286",	"critper_def":"5045",	"crithurt":"2042",	"parryper":"5286",	"parryper_dec":"5045",	"hitper":"14337",	"dodgeper":"",	"crithurt_def":"",	"recover_critper":"",	"recover_critper_def":"",	"":"",	"recover_add_fix":"",	"recover_del_fix":"",	"recover_add_per":"",	"recover_del_per":"",	"rage_add_fix":"",	"rage_del_fix":"",	"rage_add_per":"",	"rage_del_per":"" },
			{ "lv":"107",	"hp":"55302",	"physical_ack":"6573",	"physical_def":"2637",	"magic_ack":"6573",	"magic_def":"2637",	"speed":"1226",	"critper":"5336",	"critper_def":"5093",	"crithurt":"2061",	"parryper":"5336",	"parryper_dec":"5093",	"hitper":"14365",	"dodgeper":"",	"crithurt_def":"",	"recover_critper":"",	"recover_critper_def":"",	"":"",	"recover_add_fix":"",	"recover_del_fix":"",	"recover_add_per":"",	"recover_del_per":"",	"rage_add_fix":"",	"rage_del_fix":"",	"rage_add_per":"",	"rage_del_per":"" },
			{ "lv":"108",	"hp":"55559",	"physical_ack":"6603",	"physical_def":"2648",	"magic_ack":"6603",	"magic_def":"2648",	"speed":"1231",	"critper":"5385",	"critper_def":"5141",	"crithurt":"2081",	"parryper":"5385",	"parryper_dec":"5141",	"hitper":"14393",	"dodgeper":"",	"crithurt_def":"",	"recover_critper":"",	"recover_critper_def":"",	"":"",	"recover_add_fix":"",	"recover_del_fix":"",	"recover_add_per":"",	"recover_del_per":"",	"rage_add_fix":"",	"rage_del_fix":"",	"rage_add_per":"",	"rage_del_per":"" },
			{ "lv":"109",	"hp":"57306",	"physical_ack":"6831",	"physical_def":"2741",	"magic_ack":"6831",	"magic_def":"2741",	"speed":"1276",	"critper":"5435",	"critper_def":"5189",	"crithurt":"2100",	"parryper":"5435",	"parryper_dec":"5189",	"hitper":"14422",	"dodgeper":"",	"crithurt_def":"",	"recover_critper":"",	"recover_critper_def":"",	"":"",	"recover_add_fix":"",	"recover_del_fix":"",	"recover_add_per":"",	"recover_del_per":"",	"rage_add_fix":"",	"rage_del_fix":"",	"rage_add_per":"",	"rage_del_per":"" },
			{ "lv":"110",	"hp":"63843",	"physical_ack":"7675",	"physical_def":"3083",	"magic_ack":"7675",	"magic_def":"3083",	"speed":"1426",	"critper":"5485",	"critper_def":"5236",	"crithurt":"2119",	"parryper":"5485",	"parryper_dec":"5236",	"hitper":"14450",	"dodgeper":"",	"crithurt_def":"",	"recover_critper":"",	"recover_critper_def":"",	"":"",	"recover_add_fix":"",	"recover_del_fix":"",	"recover_add_per":"",	"recover_del_per":"",	"rage_add_fix":"",	"rage_del_fix":"",	"rage_add_per":"",	"rage_del_per":"" },
			{ "lv":"111",	"hp":"64084",	"physical_ack":"7716",	"physical_def":"3103",	"magic_ack":"7716",	"magic_def":"3103",	"speed":"1433",	"critper":"5535",	"critper_def":"5283",	"crithurt":"2139",	"parryper":"5535",	"parryper_dec":"5283",	"hitper":"14479",	"dodgeper":"",	"crithurt_def":"",	"recover_critper":"",	"recover_critper_def":"",	"":"",	"recover_add_fix":"",	"recover_del_fix":"",	"recover_add_per":"",	"recover_del_per":"",	"rage_add_fix":"",	"rage_del_fix":"",	"rage_add_per":"",	"rage_del_per":"" },
			{ "lv":"112",	"hp":"64849",	"physical_ack":"7815",	"physical_def":"3143",	"magic_ack":"7815",	"magic_def":"3143",	"speed":"1451",	"critper":"5585",	"critper_def":"5331",	"crithurt":"2158",	"parryper":"5585",	"parryper_dec":"5331",	"hitper":"14507",	"dodgeper":"",	"crithurt_def":"",	"recover_critper":"",	"recover_critper_def":"",	"":"",	"recover_add_fix":"",	"recover_del_fix":"",	"recover_add_per":"",	"recover_del_per":"",	"rage_add_fix":"",	"rage_del_fix":"",	"rage_add_per":"",	"rage_del_per":"" },
			{ "lv":"113",	"hp":"65155",	"physical_ack":"7849",	"physical_def":"3155",	"magic_ack":"7849",	"magic_def":"3155",	"speed":"1458",	"critper":"5635",	"critper_def":"5379",	"crithurt":"2177",	"parryper":"5635",	"parryper_dec":"5379",	"hitper":"14535",	"dodgeper":"",	"crithurt_def":"",	"recover_critper":"",	"recover_critper_def":"",	"":"",	"recover_add_fix":"",	"recover_del_fix":"",	"recover_add_per":"",	"recover_del_per":"",	"rage_add_fix":"",	"rage_del_fix":"",	"rage_add_per":"",	"rage_del_per":"" },
			{ "lv":"114",	"hp":"66540",	"physical_ack":"8038",	"physical_def":"3235",	"magic_ack":"8038",	"magic_def":"3235",	"speed":"1492",	"critper":"5685",	"critper_def":"5427",	"crithurt":"2197",	"parryper":"5685",	"parryper_dec":"5427",	"hitper":"14563",	"dodgeper":"",	"crithurt_def":"",	"recover_critper":"",	"recover_critper_def":"",	"":"",	"recover_add_fix":"",	"recover_del_fix":"",	"recover_add_per":"",	"recover_del_per":"",	"rage_add_fix":"",	"rage_del_fix":"",	"rage_add_per":"",	"rage_del_per":"" },
			{ "lv":"115",	"hp":"66854",	"physical_ack":"8072",	"physical_def":"3247",	"magic_ack":"8072",	"magic_def":"3247",	"speed":"1499",	"critper":"5735",	"critper_def":"5474",	"crithurt":"2216",	"parryper":"5735",	"parryper_dec":"5474",	"hitper":"14592",	"dodgeper":"",	"crithurt_def":"",	"recover_critper":"",	"recover_critper_def":"",	"":"",	"recover_add_fix":"",	"recover_del_fix":"",	"recover_add_per":"",	"recover_del_per":"",	"rage_add_fix":"",	"rage_del_fix":"",	"rage_add_per":"",	"rage_del_per":"" },
			{ "lv":"116",	"hp":"67691",	"physical_ack":"8193",	"physical_def":"3299",	"magic_ack":"8193",	"magic_def":"3299",	"speed":"1523",	"critper":"5785",	"critper_def":"5521",	"crithurt":"2235",	"parryper":"5785",	"parryper_dec":"5521",	"hitper":"14620",	"dodgeper":"",	"crithurt_def":"",	"recover_critper":"",	"recover_critper_def":"",	"":"",	"recover_add_fix":"",	"recover_del_fix":"",	"recover_add_per":"",	"recover_del_per":"",	"rage_add_fix":"",	"rage_del_fix":"",	"rage_add_per":"",	"rage_del_per":"" },
			{ "lv":"117",	"hp":"67997",	"physical_ack":"8228",	"physical_def":"3312",	"magic_ack":"8228",	"magic_def":"3312",	"speed":"1530",	"critper":"5835",	"critper_def":"5569",	"crithurt":"2254",	"parryper":"5835",	"parryper_dec":"5569",	"hitper":"14649",	"dodgeper":"",	"crithurt_def":"",	"recover_critper":"",	"recover_critper_def":"",	"":"",	"recover_add_fix":"",	"recover_del_fix":"",	"recover_add_per":"",	"recover_del_per":"",	"rage_add_fix":"",	"rage_del_fix":"",	"rage_add_per":"",	"rage_del_per":"" },
			{ "lv":"118",	"hp":"69622",	"physical_ack":"8340",	"physical_def":"3355",	"magic_ack":"8340",	"magic_def":"3355",	"speed":"1553",	"critper":"5884",	"critper_def":"5617",	"crithurt":"2273",	"parryper":"5884",	"parryper_dec":"5617",	"hitper":"14677",	"dodgeper":"",	"crithurt_def":"",	"recover_critper":"",	"recover_critper_def":"",	"":"",	"recover_add_fix":"",	"recover_del_fix":"",	"recover_add_per":"",	"recover_del_per":"",	"rage_add_fix":"",	"rage_del_fix":"",	"rage_add_per":"",	"rage_del_per":"" },
			{ "lv":"119",	"hp":"69888",	"physical_ack":"8380",	"physical_def":"3373",	"magic_ack":"8380",	"magic_def":"3373",	"speed":"1561",	"critper":"5934",	"critper_def":"5665",	"crithurt":"2293",	"parryper":"5934",	"parryper_dec":"5665",	"hitper":"14705",	"dodgeper":"",	"crithurt_def":"",	"recover_critper":"",	"recover_critper_def":"",	"":"",	"recover_add_fix":"",	"recover_del_fix":"",	"recover_add_per":"",	"recover_del_per":"",	"rage_add_fix":"",	"rage_del_fix":"",	"rage_add_per":"",	"rage_del_per":"" },
			{ "lv":"120",	"hp":"72955",	"physical_ack":"8642",	"physical_def":"3479",	"magic_ack":"8642",	"magic_def":"3479",	"speed":"1598",	"critper":"5984",	"critper_def":"5712",	"crithurt":"2312",	"parryper":"5984",	"parryper_dec":"5712",	"hitper":"14733",	"dodgeper":"",	"crithurt_def":"",	"recover_critper":"",	"recover_critper_def":"",	"":"",	"recover_add_fix":"",	"recover_del_fix":"",	"recover_add_per":"",	"recover_del_per":"",	"rage_add_fix":"",	"rage_del_fix":"",	"rage_add_per":"",	"rage_del_per":"" },
			{ "lv":"121",	"hp":"73205",	"physical_ack":"8684",	"physical_def":"3499",	"magic_ack":"8684",	"magic_def":"3499",	"speed":"1606",	"critper":"6034",	"critper_def":"5759",	"crithurt":"2331",	"parryper":"6034",	"parryper_dec":"5759",	"hitper":"14762",	"dodgeper":"",	"crithurt_def":"",	"recover_critper":"",	"recover_critper_def":"",	"":"",	"recover_add_fix":"",	"recover_del_fix":"",	"recover_add_per":"",	"recover_del_per":"",	"rage_add_fix":"",	"rage_del_fix":"",	"rage_add_per":"",	"rage_del_per":"" },
			{ "lv":"122",	"hp":"74187",	"physical_ack":"8808",	"physical_def":"3548",	"magic_ack":"8808",	"magic_def":"3548",	"speed":"1627",	"critper":"6084",	"critper_def":"5807",	"crithurt":"2351",	"parryper":"6084",	"parryper_dec":"5807",	"hitper":"14790",	"dodgeper":"",	"crithurt_def":"",	"recover_critper":"",	"recover_critper_def":"",	"":"",	"recover_add_fix":"",	"recover_del_fix":"",	"recover_add_per":"",	"recover_del_per":"",	"rage_add_fix":"",	"rage_del_fix":"",	"rage_add_per":"",	"rage_del_per":"" },
			{ "lv":"123",	"hp":"74493",	"physical_ack":"8842",	"physical_def":"3560",	"magic_ack":"8842",	"magic_def":"3560",	"speed":"1634",	"critper":"6133",	"critper_def":"5855",	"crithurt":"2370",	"parryper":"6133",	"parryper_dec":"5855",	"hitper":"14819",	"dodgeper":"",	"crithurt_def":"",	"recover_critper":"",	"recover_critper_def":"",	"":"",	"recover_add_fix":"",	"recover_del_fix":"",	"recover_add_per":"",	"recover_del_per":"",	"rage_add_fix":"",	"rage_del_fix":"",	"rage_add_per":"",	"rage_del_per":"" },
			{ "lv":"124",	"hp":"76223",	"physical_ack":"9076",	"physical_def":"3658",	"magic_ack":"9076",	"magic_def":"3658",	"speed":"1679",	"critper":"6183",	"critper_def":"5903",	"crithurt":"2389",	"parryper":"6183",	"parryper_dec":"5903",	"hitper":"14847",	"dodgeper":"",	"crithurt_def":"",	"recover_critper":"",	"recover_critper_def":"",	"":"",	"recover_add_fix":"",	"recover_del_fix":"",	"recover_add_per":"",	"recover_del_per":"",	"rage_add_fix":"",	"rage_del_fix":"",	"rage_add_per":"",	"rage_del_per":"" },
			{ "lv":"125",	"hp":"78083",	"physical_ack":"9315",	"physical_def":"3755",	"magic_ack":"9315",	"magic_def":"3755",	"speed":"1728",	"critper":"6233",	"critper_def":"5950",	"crithurt":"2409",	"parryper":"6233",	"parryper_dec":"5950",	"hitper":"14875",	"dodgeper":"",	"crithurt_def":"",	"recover_critper":"",	"recover_critper_def":"",	"":"",	"recover_add_fix":"",	"recover_del_fix":"",	"recover_add_per":"",	"recover_del_per":"",	"rage_add_fix":"",	"rage_del_fix":"",	"rage_add_per":"",	"rage_del_per":"" },
			{ "lv":"126",	"hp":"78324",	"physical_ack":"9357",	"physical_def":"3775",	"magic_ack":"9357",	"magic_def":"3775",	"speed":"1733",	"critper":"6283",	"critper_def":"5997",	"crithurt":"2427",	"parryper":"6283",	"parryper_dec":"5997",	"hitper":"14903",	"dodgeper":"",	"crithurt_def":"",	"recover_critper":"",	"recover_critper_def":"",	"":"",	"recover_add_fix":"",	"recover_del_fix":"",	"recover_add_per":"",	"recover_del_per":"",	"rage_add_fix":"",	"rage_del_fix":"",	"rage_add_per":"",	"rage_del_per":"" },
			{ "lv":"127",	"hp":"79162",	"physical_ack":"9458",	"physical_def":"3814",	"magic_ack":"9458",	"magic_def":"3814",	"speed":"1753",	"critper":"6333",	"critper_def":"6045",	"crithurt":"2447",	"parryper":"6333",	"parryper_dec":"6045",	"hitper":"14932",	"dodgeper":"",	"crithurt_def":"",	"recover_critper":"",	"recover_critper_def":"",	"":"",	"recover_add_fix":"",	"recover_del_fix":"",	"recover_add_per":"",	"recover_del_per":"",	"rage_add_fix":"",	"rage_del_fix":"",	"rage_add_per":"",	"rage_del_per":"" },
			{ "lv":"128",	"hp":"79459",	"physical_ack":"9493",	"physical_def":"3827",	"magic_ack":"9493",	"magic_def":"3827",	"speed":"1759",	"critper":"6383",	"critper_def":"6093",	"crithurt":"2466",	"parryper":"6383",	"parryper_dec":"6093",	"hitper":"14960",	"dodgeper":"",	"crithurt_def":"",	"recover_critper":"",	"recover_critper_def":"",	"":"",	"recover_add_fix":"",	"recover_del_fix":"",	"recover_add_per":"",	"recover_del_per":"",	"rage_add_fix":"",	"rage_del_fix":"",	"rage_add_per":"",	"rage_del_per":"" },
			{ "lv":"129",	"hp":"80997",	"physical_ack":"9691",	"physical_def":"3908",	"magic_ack":"9691",	"magic_def":"3908",	"speed":"1800",	"critper":"6433",	"critper_def":"6141",	"crithurt":"2485",	"parryper":"6433",	"parryper_dec":"6141",	"hitper":"14989",	"dodgeper":"",	"crithurt_def":"",	"recover_critper":"",	"recover_critper_def":"",	"":"",	"recover_add_fix":"",	"recover_del_fix":"",	"recover_add_per":"",	"recover_del_per":"",	"rage_add_fix":"",	"rage_del_fix":"",	"rage_add_per":"",	"rage_del_per":"" },
			{ "lv":"130",	"hp":"86954",	"physical_ack":"10528",	"physical_def":"4221",	"magic_ack":"10528",	"magic_def":"4221",	"speed":"1930",	"critper":"6483",	"critper_def":"6188",	"crithurt":"2505",	"parryper":"6483",	"parryper_dec":"6188",	"hitper":"15017",	"dodgeper":"",	"crithurt_def":"",	"recover_critper":"",	"recover_critper_def":"",	"":"",	"recover_add_fix":"",	"recover_del_fix":"",	"recover_add_per":"",	"recover_del_per":"",	"rage_add_fix":"",	"rage_del_fix":"",	"rage_add_per":"",	"rage_del_per":"" },
			{ "lv":"131",	"hp":"87880",	"physical_ack":"10662",	"physical_def":"4279",	"magic_ack":"10662",	"magic_def":"4279",	"speed":"1955",	"critper":"6533",	"critper_def":"6235",	"crithurt":"2524",	"parryper":"6533",	"parryper_dec":"6235",	"hitper":"15045",	"dodgeper":"",	"crithurt_def":"",	"recover_critper":"",	"recover_critper_def":"",	"":"",	"recover_add_fix":"",	"recover_del_fix":"",	"recover_add_per":"",	"recover_del_per":"",	"rage_add_fix":"",	"rage_del_fix":"",	"rage_add_per":"",	"rage_del_per":"" },
			{ "lv":"132",	"hp":"88226",	"physical_ack":"10701",	"physical_def":"4293",	"magic_ack":"10701",	"magic_def":"4293",	"speed":"1962",	"critper":"6583",	"critper_def":"6283",	"crithurt":"2543",	"parryper":"6583",	"parryper_dec":"6283",	"hitper":"15073",	"dodgeper":"",	"crithurt_def":"",	"recover_critper":"",	"recover_critper_def":"",	"":"",	"recover_add_fix":"",	"recover_del_fix":"",	"recover_add_per":"",	"recover_del_per":"",	"rage_add_fix":"",	"rage_del_fix":"",	"rage_add_per":"",	"rage_del_per":"" },
			{ "lv":"133",	"hp":"90298",	"physical_ack":"10828",	"physical_def":"4343",	"magic_ack":"10828",	"magic_def":"4343",	"speed":"1985",	"critper":"6632",	"critper_def":"6331",	"crithurt":"2563",	"parryper":"6632",	"parryper_dec":"6331",	"hitper":"15102",	"dodgeper":"",	"crithurt_def":"",	"recover_critper":"",	"recover_critper_def":"",	"":"",	"recover_add_fix":"",	"recover_del_fix":"",	"recover_add_per":"",	"recover_del_per":"",	"rage_add_fix":"",	"rage_del_fix":"",	"rage_add_per":"",	"rage_del_per":"" },
			{ "lv":"134",	"hp":"90580",	"physical_ack":"10875",	"physical_def":"4365",	"magic_ack":"10875",	"magic_def":"4365",	"speed":"1993",	"critper":"6682",	"critper_def":"6379",	"crithurt":"2582",	"parryper":"6682",	"parryper_dec":"6379",	"hitper":"15130",	"dodgeper":"",	"crithurt_def":"",	"recover_critper":"",	"recover_critper_def":"",	"":"",	"recover_add_fix":"",	"recover_del_fix":"",	"recover_add_per":"",	"recover_del_per":"",	"rage_add_fix":"",	"rage_del_fix":"",	"rage_add_per":"",	"rage_del_per":"" },
			{ "lv":"135",	"hp":"92262",	"physical_ack":"11092",	"physical_def":"4453",	"magic_ack":"11092",	"magic_def":"4453",	"speed":"2036",	"critper":"6732",	"critper_def":"6426",	"crithurt":"2601",	"parryper":"6732",	"parryper_dec":"6426",	"hitper":"15159",	"dodgeper":"",	"crithurt_def":"",	"recover_critper":"",	"recover_critper_def":"",	"":"",	"recover_add_fix":"",	"recover_del_fix":"",	"recover_add_per":"",	"recover_del_per":"",	"rage_add_fix":"",	"rage_del_fix":"",	"rage_add_per":"",	"rage_del_per":"" },
			{ "lv":"136",	"hp":"92552",	"physical_ack":"11139",	"physical_def":"4475",	"magic_ack":"11139",	"magic_def":"4475",	"speed":"2043",	"critper":"6782",	"critper_def":"6473",	"crithurt":"2620",	"parryper":"6782",	"parryper_dec":"6473",	"hitper":"15187",	"dodgeper":"",	"crithurt_def":"",	"recover_critper":"",	"recover_critper_def":"",	"":"",	"recover_add_fix":"",	"recover_del_fix":"",	"recover_add_per":"",	"recover_del_per":"",	"rage_add_fix":"",	"rage_del_fix":"",	"rage_add_per":"",	"rage_del_per":"" },
			{ "lv":"137",	"hp":"93663",	"physical_ack":"11276",	"physical_def":"4529",	"magic_ack":"11276",	"magic_def":"4529",	"speed":"2070",	"critper":"6832",	"critper_def":"6521",	"crithurt":"2639",	"parryper":"6832",	"parryper_dec":"6521",	"hitper":"15215",	"dodgeper":"",	"crithurt_def":"",	"recover_critper":"",	"recover_critper_def":"",	"":"",	"recover_add_fix":"",	"recover_del_fix":"",	"recover_add_per":"",	"recover_del_per":"",	"rage_add_fix":"",	"rage_del_fix":"",	"rage_add_per":"",	"rage_del_per":"" },
			{ "lv":"138",	"hp":"94017",	"physical_ack":"11315",	"physical_def":"4543",	"magic_ack":"11315",	"magic_def":"4543",	"speed":"2077",	"critper":"6881",	"critper_def":"6569",	"crithurt":"2659",	"parryper":"6881",	"parryper_dec":"6569",	"hitper":"15243",	"dodgeper":"",	"crithurt_def":"",	"recover_critper":"",	"recover_critper_def":"",	"":"",	"recover_add_fix":"",	"recover_del_fix":"",	"recover_add_per":"",	"recover_del_per":"",	"rage_add_fix":"",	"rage_del_fix":"",	"rage_add_per":"",	"rage_del_per":"" },
			{ "lv":"139",	"hp":"95917",	"physical_ack":"11573",	"physical_def":"4651",	"magic_ack":"11573",	"magic_def":"4651",	"speed":"2128",	"critper":"6931",	"critper_def":"6617",	"crithurt":"2678",	"parryper":"6931",	"parryper_dec":"6617",	"hitper":"15272",	"dodgeper":"",	"crithurt_def":"",	"recover_critper":"",	"recover_critper_def":"",	"":"",	"recover_add_fix":"",	"recover_del_fix":"",	"recover_add_per":"",	"recover_del_per":"",	"rage_add_fix":"",	"rage_del_fix":"",	"rage_add_per":"",	"rage_del_per":"" },
			{ "lv":"140",	"hp":"99749",	"physical_ack":"12004",	"physical_def":"4799",	"magic_ack":"12004",	"magic_def":"4799",	"speed":"2189",	"critper":"6981",	"critper_def":"6664",	"crithurt":"2697",	"parryper":"6981",	"parryper_dec":"6664",	"hitper":"15300",	"dodgeper":"",	"crithurt_def":"",	"recover_critper":"",	"recover_critper_def":"",	"":"",	"recover_add_fix":"",	"recover_del_fix":"",	"recover_add_per":"",	"recover_del_per":"",	"rage_add_fix":"",	"rage_del_fix":"",	"rage_add_per":"",	"rage_del_per":"" },
			{ "lv":"141",	"hp":"100047",	"physical_ack":"12050",	"physical_def":"4820",	"magic_ack":"12050",	"magic_def":"4820",	"speed":"2196",	"critper":"7031",	"critper_def":"6711",	"crithurt":"2717",	"parryper":"7031",	"parryper_dec":"6711",	"hitper":"15329",	"dodgeper":"",	"crithurt_def":"",	"recover_critper":"",	"recover_critper_def":"",	"":"",	"recover_add_fix":"",	"recover_del_fix":"",	"recover_add_per":"",	"recover_del_per":"",	"rage_add_fix":"",	"rage_del_fix":"",	"rage_add_per":"",	"rage_del_per":"" },
			{ "lv":"142",	"hp":"101053",	"physical_ack":"12177",	"physical_def":"4871",	"magic_ack":"12177",	"magic_def":"4871",	"speed":"2221",	"critper":"7081",	"critper_def":"6759",	"crithurt":"2736",	"parryper":"7081",	"parryper_dec":"6759",	"hitper":"15357",	"dodgeper":"",	"crithurt_def":"",	"recover_critper":"",	"recover_critper_def":"",	"":"",	"recover_add_fix":"",	"recover_del_fix":"",	"recover_add_per":"",	"recover_del_per":"",	"rage_add_fix":"",	"rage_del_fix":"",	"rage_add_per":"",	"rage_del_per":"" },
			{ "lv":"143",	"hp":"101407",	"physical_ack":"12216",	"physical_def":"4885",	"magic_ack":"12216",	"magic_def":"4885",	"speed":"2228",	"critper":"7131",	"critper_def":"6807",	"crithurt":"2755",	"parryper":"7131",	"parryper_dec":"6807",	"hitper":"15385",	"dodgeper":"",	"crithurt_def":"",	"recover_critper":"",	"recover_critper_def":"",	"":"",	"recover_add_fix":"",	"recover_del_fix":"",	"recover_add_per":"",	"recover_del_per":"",	"rage_add_fix":"",	"rage_del_fix":"",	"rage_add_per":"",	"rage_del_per":"" },
			{ "lv":"144",	"hp":"103267",	"physical_ack":"12469",	"physical_def":"4991",	"magic_ack":"12469",	"magic_def":"4991",	"speed":"2277",	"critper":"7181",	"critper_def":"6855",	"crithurt":"2775",	"parryper":"7181",	"parryper_dec":"6855",	"hitper":"15413",	"dodgeper":"",	"crithurt_def":"",	"recover_critper":"",	"recover_critper_def":"",	"":"",	"recover_add_fix":"",	"recover_del_fix":"",	"recover_add_per":"",	"recover_del_per":"",	"rage_add_fix":"",	"rage_del_fix":"",	"rage_add_per":"",	"rage_del_per":"" },
			{ "lv":"145",	"hp":"103605",	"physical_ack":"12509",	"physical_def":"5006",	"magic_ack":"12509",	"magic_def":"5006",	"speed":"2284",	"critper":"7231",	"critper_def":"6902",	"crithurt":"2794",	"parryper":"7231",	"parryper_dec":"6902",	"hitper":"15442",	"dodgeper":"",	"crithurt_def":"",	"recover_critper":"",	"recover_critper_def":"",	"":"",	"recover_add_fix":"",	"recover_del_fix":"",	"recover_add_per":"",	"recover_del_per":"",	"rage_add_fix":"",	"rage_del_fix":"",	"rage_add_per":"",	"rage_del_per":"" },
			{ "lv":"146",	"hp":"104780",	"physical_ack":"12664",	"physical_def":"5071",	"magic_ack":"12664",	"magic_def":"5071",	"speed":"2311",	"critper":"7281",	"critper_def":"6949",	"crithurt":"2813",	"parryper":"7281",	"parryper_dec":"6949",	"hitper":"15470",	"dodgeper":"",	"crithurt_def":"",	"recover_critper":"",	"recover_critper_def":"",	"":"",	"recover_add_fix":"",	"recover_del_fix":"",	"recover_add_per":"",	"recover_del_per":"",	"rage_add_fix":"",	"rage_del_fix":"",	"rage_add_per":"",	"rage_del_per":"" },
			{ "lv":"147",	"hp":"105126",	"physical_ack":"12704",	"physical_def":"5085",	"magic_ack":"12704",	"magic_def":"5085",	"speed":"2318",	"critper":"7331",	"critper_def":"6997",	"crithurt":"2832",	"parryper":"7331",	"parryper_dec":"6997",	"hitper":"15499",	"dodgeper":"",	"crithurt_def":"",	"recover_critper":"",	"recover_critper_def":"",	"":"",	"recover_add_fix":"",	"recover_del_fix":"",	"recover_add_per":"",	"recover_del_per":"",	"rage_add_fix":"",	"rage_del_fix":"",	"rage_add_per":"",	"rage_del_per":"" },
			{ "lv":"148",	"hp":"107368",	"physical_ack":"12853",	"physical_def":"5144",	"magic_ack":"12853",	"magic_def":"5144",	"speed":"2351",	"critper":"7380",	"critper_def":"7045",	"crithurt":"2851",	"parryper":"7380",	"parryper_dec":"7045",	"hitper":"15527",	"dodgeper":"",	"crithurt_def":"",	"recover_critper":"",	"recover_critper_def":"",	"":"",	"recover_add_fix":"",	"recover_del_fix":"",	"recover_add_per":"",	"recover_del_per":"",	"rage_add_fix":"",	"rage_del_fix":"",	"rage_add_per":"",	"rage_del_per":"" },
			{ "lv":"149",	"hp":"107658",	"physical_ack":"12900",	"physical_def":"5166",	"magic_ack":"12900",	"magic_def":"5166",	"speed":"2358",	"critper":"7430",	"critper_def":"7093",	"crithurt":"2871",	"parryper":"7430",	"parryper_dec":"7093",	"hitper":"15555",	"dodgeper":"",	"crithurt_def":"",	"recover_critper":"",	"recover_critper_def":"",	"":"",	"recover_add_fix":"",	"recover_del_fix":"",	"recover_add_per":"",	"recover_del_per":"",	"rage_add_fix":"",	"rage_del_fix":"",	"rage_add_per":"",	"rage_del_per":"" },
			{ "lv":"150",	"hp":"109751",	"physical_ack":"13162",	"physical_def":"5270",	"magic_ack":"13162",	"magic_def":"5270",	"speed":"2410",	"critper":"7480",	"critper_def":"7140",	"crithurt":"2890",	"parryper":"7480",	"parryper_dec":"7140",	"hitper":"15583",	"dodgeper":"",	"crithurt_def":"",	"recover_critper":"",	"recover_critper_def":"",	"":"",	"recover_add_fix":"",	"recover_del_fix":"",	"recover_add_per":"",	"recover_del_per":"",	"rage_add_fix":"",	"rage_del_fix":"",	"rage_add_per":"",	"rage_del_per":"" }
		]
}
